easyRun/NOTcountingFolds.py
easyRun/__init__.py
easyRun/countFolds.py
easyRun/eliminateFolds.py
easyRun/generateAllModules.py
easyRun/meanders.py
mapFolding/__init__.py
mapFolding/_theSSOT.py
mapFolding/_theTypes.py
mapFolding/basecamp.py
mapFolding/beDRY.py
mapFolding/dataBaskets.py
mapFolding/filesystemToolkit.py
mapFolding/oeis.py
mapFolding/py.typed
mapFolding/algorithms/A086345.py
mapFolding/algorithms/__init__.py
mapFolding/algorithms/constraintPropagation.py
mapFolding/algorithms/daoOfMapFolding.py
mapFolding/algorithms/elimination.py
mapFolding/algorithms/eliminationCount.py
mapFolding/algorithms/eliminationPinned.py
mapFolding/algorithms/iff.py
mapFolding/algorithms/matrixMeanders.py
mapFolding/algorithms/matrixMeandersNumPyndas.py
mapFolding/algorithms/oeisIDbyFormula.py
mapFolding/algorithms/patternFinder.py
mapFolding/algorithms/pinning2Dn.py
mapFolding/algorithms/pinning2DnAnnex.py
mapFolding/algorithms/symmetricFolds.py
mapFolding/algorithms/zCuzDocStoopidoeisIDbyFormula.py
mapFolding/reference/A000682facts.py
mapFolding/reference/A005316facts.py
mapFolding/reference/A086345Wu.py
mapFolding/reference/__init__.py
mapFolding/reference/flattened.py
mapFolding/reference/hunterNumba.py
mapFolding/reference/irvineJavaPort.py
mapFolding/reference/jaxCount.py
mapFolding/reference/lunnonNumpy.py
mapFolding/reference/lunnonWhile.py
mapFolding/reference/rotatedEntryPoint.py
mapFolding/reference/total_countPlus1vsPlusN.py
mapFolding/reference/jobsCompleted/__init__.py
mapFolding/reference/jobsCompleted/[2x19]/p2x19.py
mapFolding/reference/jobsCompleted/p2x19/p2x19.py
mapFolding/reference/matrixMeandersAnalysis/__init__.py
mapFolding/reference/matrixMeandersAnalysis/prefixNotationNotes.py
mapFolding/reference/matrixMeandersAnalysis/signatures.py
mapFolding/reference/meandersDumpingGround/A005316JavaPort.py
mapFolding/reference/meandersDumpingGround/A005316imperative.py
mapFolding/reference/meandersDumpingGround/A005316primitiveOptimized.py
mapfolding-0.17.1.dist-info/licenses/LICENSE
mapfolding-0.17.1.dist-info/METADATA
mapfolding-0.17.1.dist-info/WHEEL
mapfolding-0.17.1.dist-info/entry_points.txt
mapfolding-0.17.1.dist-info/top_level.txt
mapfolding-0.17.1.dist-info/RECORD
