Metadata-Version: 2.4
Name: mapFolding
Version: 0.17.1
Summary: Map folding, meanders, stamp folding, semi-meanders. Experiment with algorithm transformations, and analyze computational states.
Author-email: Hunter Hogan <HunterHogan@pm.me>
License: CC-BY-NC-4.0
Project-URL: Donate, https://www.patreon.com/integrated
Project-URL: Homepage, https://github.com/hunterhogan/mapFolding
Project-URL: Issues, https://github.com/hunterhogan/mapFolding/issues
Project-URL: Repository, https://github.com/hunterhogan/mapFolding.git
Keywords: A000136,A000560,A000682,A001010,A001011,A001415,A001416,A001417,A001418,A005315,A005316,A007822,A178961,A195646,A223094,A259702,A301620,AST manipulation,JIT compilation,Numba optimization,OEIS,Python optimization,abstract syntax tree,algorithmic combinatorics,algorithmic optimization,arch configurations,automated code generation,bit-packed arrays,bitwise state machines,cache-efficient algorithms,closed meandric numbers,code generation,code optimization,code synthesis,code transformatio
Classifier: Development Status :: 4 - Beta
Classifier: Environment :: Console
Classifier: Intended Audience :: Developers
Classifier: Intended Audience :: Education
Classifier: Intended Audience :: Science/Research
Classifier: Natural Language :: English
Classifier: Operating System :: MacOS
Classifier: Operating System :: OS Independent
Classifier: Operating System :: POSIX :: Linux
Classifier: Programming Language :: Python
Classifier: Programming Language :: Python :: 3
Classifier: Programming Language :: Python :: 3 :: Only
Classifier: Programming Language :: Python :: 3.12
Classifier: Programming Language :: Python :: 3.13
Classifier: Programming Language :: Python :: Implementation :: CPython
Classifier: Topic :: Scientific/Engineering :: Information Analysis
Classifier: Topic :: Scientific/Engineering :: Mathematics
Classifier: Topic :: Software Development :: Code Generators
Classifier: Topic :: Software Development :: Compilers
Classifier: Topic :: Software Development :: Libraries :: Python Modules
Classifier: Topic :: Software Development :: Pre-processors
Classifier: Typing :: Typed
Requires-Python: <3.14,>=3.12
License-File: LICENSE
Requires-Dist: astToolkit>=0.9.0
Requires-Dist: cytoolz
Requires-Dist: gmpy2
Requires-Dist: hunterMakesPy>=0.3.0
Requires-Dist: more_itertools
Requires-Dist: numpy
Requires-Dist: platformdirs
Provides-Extra: development
Requires-Dist: ipykernel; extra == "development"
Requires-Dist: ipywidgets; extra == "development"
Requires-Dist: memray; sys_platform == "linux" and extra == "development"
Requires-Dist: py-spy; extra == "development"
Requires-Dist: pyarrow-stubs; extra == "development"
Requires-Dist: setuptools-scm; extra == "development"
Provides-Extra: numba
Requires-Dist: numba; extra == "numba"
Requires-Dist: numba_progress; extra == "numba"
Provides-Extra: pandas
Requires-Dist: ortools; extra == "pandas"
Requires-Dist: pandas; extra == "pandas"
Requires-Dist: pyarrow; extra == "pandas"
Provides-Extra: sympy
Requires-Dist: sympy; extra == "sympy"
Provides-Extra: testing
Requires-Dist: numba; extra == "testing"
Requires-Dist: ortools; extra == "testing"
Requires-Dist: pandas; extra == "testing"
Requires-Dist: pyarrow; extra == "testing"
Requires-Dist: pytest-cov; extra == "testing"
Requires-Dist: pytest-env; extra == "testing"
Requires-Dist: pytest-xdist; extra == "testing"
Requires-Dist: pytest; extra == "testing"
Requires-Dist: sympy; extra == "testing"
Dynamic: license-file
